tinybio/__init__.py
tinybio/tinybio.py
tinybio-0.1.0.dist-info/LICENSE
tinybio-0.1.0.dist-info/METADATA
tinybio-0.1.0.dist-info/WHEEL
tinybio-0.1.0.dist-info/top_level.txt
tinybio-0.1.0.dist-info/RECORD
